FlaskTrytonWTF/FTFT.py
FlaskTrytonWTF/FTWTF.py
FlaskTrytonWTF/__init__.py
FlaskTrytonWTF/convetion.py
FlaskTrytonWTF/widgets.py
FlaskTrytonWTF-0.0.4.dist-info/METADATA
FlaskTrytonWTF-0.0.4.dist-info/WHEEL
FlaskTrytonWTF-0.0.4.dist-info/top_level.txt
FlaskTrytonWTF-0.0.4.dist-info/RECORD
