Metadata-Version: 2.1
Name: FlaskTrytonWTF
Version: 0.0.4
Summary: The project intend to or extendig the capabilities of flask in order to read and write data directely to tryton.
Home-page: https://bitbucket.org/omniasolutions/flasktrytonwtf/src/master/
Author: Matteo Boscolo
Author-email: matteo.boscolo@omniasolutions.eu
License: UNKNOWN
Platform: UNKNOWN
Classifier: Programming Language :: Python :: 3
Classifier: License :: OSI Approved :: GNU Lesser General Public License v3 (LGPLv3)
Classifier: Operating System :: OS Independent
Requires-Dist: Flask-Table
Requires-Dist: Flask-WTF
Requires-Dist: flask-tryton
